{
  "manifest_version": 2,
  "name": "Nodanium下载器",
  "version": "1.0.0",
  "description": "Nodanium的附属插件",
  "permissions": [
    "activeTab",
    "storage",
    "downloads",
    "webRequest",
    "webRequestBlocking",
    "nativeMessaging",
    "<all_urls>"
  ],
  "background": {
    "scripts": ["polyfill.js", "background.js"],
    "persistent": true
  },
  "browser_action": {
    "default_popup": "popup.html",
    "default_icon": {
      "16": "icons/icon.png",
      "48": "icons/icon.png",
      "128": "icons/icon.png"
    }
  },
  "content_scripts": [
    {
      "matches": ["<all_urls>"],
      "js": ["polyfill.js", "content.js"],
      "run_at": "document_start"
    }
  ],
  "icons": {
    "16": "icons/icon.png",
    "48": "icons/icon.png",
    "128": "icons/icon.png"
  },
  "applications": {
    "gecko": {
      "id": "downloader@example.com",
      "strict_min_version": "50.0"
    }
  }
}